quatorzeheures/__init__.py
quatorzeheures/main.py
quatorzeheures/test/test_quatorzeheures.py
quatorzeheures-0.1.2.dist-info/DESCRIPTION.rst
quatorzeheures-0.1.2.dist-info/METADATA
quatorzeheures-0.1.2.dist-info/RECORD
quatorzeheures-0.1.2.dist-info/WHEEL
quatorzeheures-0.1.2.dist-info/entry_points.txt
quatorzeheures-0.1.2.dist-info/metadata.json
quatorzeheures-0.1.2.dist-info/top_level.txt
